{
    "Data": {
        "340": [
            {
                "AethernetID": 1966102,
                "Front": {
                    "X": 121.167206,
                    "Y": 43.762955,
                    "Z": -78.47423
                }
            },
            {
                "AethernetID": 1966102,
                "Front": {
                    "X": 78.53364,
                    "Y": 48.747097,
                    "Z": -81.5487
                }
            },
            {
                "AethernetID": 1966097,
                "Front": {
                    "X": 103.737366,
                    "Y": 57.870335,
                    "Z": -155.71565
                }
            },
            {
                "AethernetID": 1966102,
                "Front": {
                    "X": 56.811577,
                    "Y": 52.91755,
                    "Z": -76.47101
                }
            },
            {
                "AethernetID": 1966102,
                "Front": {
                    "X": 71.62517,
                    "Y": 32.243996,
                    "Z": -7.81905
                }
            },
            {
                "AethernetID": 1966102,
                "Front": {
                    "X": 121.3612,
                    "Y": 22.482094,
                    "Z": 19.82366
                }
            },
            {
                "AethernetID": 1966100,
                "Front": {
                    "X": 115.01598,
                    "Y": 7.614976,
                    "Z": 69.92499
                }
            },
            {
                "AethernetID": 1966100,
                "Front": {
                    "X": 97.859886,
                    "Y": 7.120797,
                    "Z": 76.06029
                }
            },
            {
                "AethernetID": 1966100,
                "Front": {
                    "X": 106.92946,
                    "Y": 6.145767,
                    "Z": 95.11165
                }
            },
            {
                "AethernetID": 1966100,
                "Front": {
                    "X": 91.901505,
                    "Y": 5.5253744,
                    "Z": 99.98674
                }
            },
            {
                "AethernetID": 1966100,
                "Front": {
                    "X": 52.292854,
                    "Y": 2.3984938,
                    "Z": 155.49458
                }
            },
            {
                "AethernetID": 1966102,
                "Front": {
                    "X": 82.246284,
                    "Y": 22.979368,
                    "Z": 22.556469
                }
            },
            {
                "AethernetID": 1966102,
                "Front": {
                    "X": 45.16124,
                    "Y": 32.141026,
                    "Z": 8.408286
                }
            },
            {
                "AethernetID": 1966102,
                "Front": {
                    "X": 50.254536,
                    "Y": 17.81252,
                    "Z": 43.38225
                }
            },
            {
                "AethernetID": 1966101,
                "Front": {
                    "X": -77.391914,
                    "Y": 5.66529,
                    "Z": 115.52193
                }
            },
            {
                "AethernetID": 1966101,
                "Front": {
                    "X": -77.493935,
                    "Y": 5.6754684,
                    "Z": 115.331924
                }
            },
            {
                "AethernetID": 1966101,
                "Front": {
                    "X": -42.933697,
                    "Y": 8.195208,
                    "Z": 91.2095
                }
            },
            {
                "AethernetID": 1966099,
                "Front": {
                    "X": -12.04911,
                    "Y": 18.712286,
                    "Z": 44.565063
                }
            },
            {
                "AethernetID": 1966101,
                "Front": {
                    "X": -64.72194,
                    "Y": 19.718264,
                    "Z": 51.67939
                }
            },
            {
                "AethernetID": 1966099,
                "Front": {
                    "X": -26.725088,
                    "Y": 30.90668,
                    "Z": 1.1362429
                }
            },
            {
                "AethernetID": 1966098,
                "Front": {
                    "X": -57.81827,
                    "Y": 28.433643,
                    "Z": 19.27686
                }
            },
            {
                "AethernetID": 1966099,
                "Front": {
                    "X": -18.865236,
                    "Y": 39.51287,
                    "Z": -36.5963
                }
            },
            {
                "AethernetID": 1966098,
                "Front": {
                    "X": -83.217026,
                    "Y": 30.135756,
                    "Z": -35.32551
                }
            },
            {
                "AethernetID": 1966099,
                "Front": {
                    "X": -27.202835,
                    "Y": 45.17744,
                    "Z": -65.265656
                }
            },
            {
                "AethernetID": 1966099,
                "Front": {
                    "X": -21.64618,
                    "Y": 44.867943,
                    "Z": -73.06179
                }
            },
            {
                "AethernetID": 1966097,
                "Front": {
                    "X": -31.901653,
                    "Y": 54.66039,
                    "Z": -123.57272
                }
            },
            {
                "AethernetID": 1966098,
                "Front": {
                    "X": -92.46556,
                    "Y": 29.47563,
                    "Z": -34.009888
                }
            },
            {
                "AethernetID": 1966098,
                "Front": {
                    "X": -110.876915,
                    "Y": 27.545006,
                    "Z": -104.23054
                }
            },
            {
                "AethernetID": 1966098,
                "Front": {
                    "X": -94.82238,
                    "Y": 34.687927,
                    "Z": -143.13196
                }
            },
            {
                "AethernetID": 1966098,
                "Front": {
                    "X": -50.46832,
                    "Y": 53.86013,
                    "Z": -127.30198
                }
            },
            {
                "AethernetID": 1966105,
                "Front": {
                    "X": -625.59424,
                    "Y": 43.761234,
                    "Z": -582.64404
                }
            },
            {
                "AethernetID": 1966110,
                "Front": {
                    "X": -622.28766,
                    "Y": 48.754017,
                    "Z": -625.4223
                }
            },
            {
                "AethernetID": 1966105,
                "Front": {
                    "X": -548.3751,
                    "Y": 57.87034,
                    "Z": -599.9281
                }
            },
            {
                "AethernetID": 1966105,
                "Front": {
                    "X": -627.83875,
                    "Y": 52.917564,
                    "Z": -647.2731
                }
            },
            {
                "AethernetID": 1966110,
                "Front": {
                    "X": -695.8578,
                    "Y": 32.27763,
                    "Z": -632.63007
                }
            },
            {
                "AethernetID": 1966110,
                "Front": {
                    "X": -723.5153,
                    "Y": 22.66876,
                    "Z": -582.02216
                }
            },
            {
                "AethernetID": 1966108,
                "Front": {
                    "X": -773.8836,
                    "Y": 7.619833,
                    "Z": -589.04266
                }
            },
            {
                "AethernetID": 1966108,
                "Front": {
                    "X": -780.17596,
                    "Y": 7.1209097,
                    "Z": -606.356
                }
            },
            {
                "AethernetID": 1966108,
                "Front": {
                    "X": -798.8268,
                    "Y": 6.1564207,
                    "Z": -596.9192
                }
            },
            {
                "AethernetID": 1966108,
                "Front": {
                    "X": -803.9629,
                    "Y": 5.5242786,
                    "Z": -612.22577
                }
            },
            {
                "AethernetID": 1966111,
                "Front": {
                    "X": -859.23987,
                    "Y": 2.3984938,
                    "Z": -651.9619
                }
            },
            {
                "AethernetID": 1966110,
                "Front": {
                    "X": -726.6742,
                    "Y": 22.94008,
                    "Z": -621.5536
                }
            },
            {
                "AethernetID": 1966110,
                "Front": {
                    "X": -712.3094,
                    "Y": 32.13713,
                    "Z": -658.54663
                }
            },
            {
                "AethernetID": 1966108,
                "Front": {
                    "X": -747.4987,
                    "Y": 17.80505,
                    "Z": -654.1082
                }
            },
            {
                "AethernetID": 1966109,
                "Front": {
                    "X": -785.6516,
                    "Y": 7.0405436,
                    "Z": -673.8352
                }
            },
            {
                "AethernetID": 1966109,
                "Front": {
                    "X": -819.5188,
                    "Y": 5.673649,
                    "Z": -781.62823
                }
            },
            {
                "AethernetID": 1966109,
                "Front": {
                    "X": -795.2663,
                    "Y": 8.199364,
                    "Z": -746.8827
                }
            },
            {
                "AethernetID": 1966107,
                "Front": {
                    "X": -748.6791,
                    "Y": 18.832743,
                    "Z": -716.6167
                }
            },
            {
                "AethernetID": 1966109,
                "Front": {
                    "X": -755.7862,
                    "Y": 19.696512,
                    "Z": -769.38574
                }
            },
            {
                "AethernetID": 1966107,
                "Front": {
                    "X": -704.9797,
                    "Y": 30.910738,
                    "Z": -730.7525
                }
            },
            {
                "AethernetID": 1966106,
                "Front": {
                    "X": -723.4701,
                    "Y": 28.414959,
                    "Z": -762.0117
                }
            },
            {
                "AethernetID": 1966107,
                "Front": {
                    "X": -667.62427,
                    "Y": 39.51287,
                    "Z": -722.94104
                }
            },
            {
                "AethernetID": 1966106,
                "Front": {
                    "X": -668.52924,
                    "Y": 30.119852,
                    "Z": -787.38885
                }
            },
            {
                "AethernetID": 1966107,
                "Front": {
                    "X": -638.7553,
                    "Y": 45.17941,
                    "Z": -731.24554
                }
            },
            {
                "AethernetID": 1966107,
                "Front": {
                    "X": -631.00256,
                    "Y": 44.869053,
                    "Z": -725.6588
                }
            },
            {
                "AethernetID": 1966105,
                "Front": {
                    "X": -580.58386,
                    "Y": 54.643784,
                    "Z": -735.87115
                }
            },
            {
                "AethernetID": 1966106,
                "Front": {
                    "X": -669.9531,
                    "Y": 29.474787,
                    "Z": -796.48676
                }
            },
            {
                "AethernetID": 1966106,
                "Front": {
                    "X": -599.6197,
                    "Y": 27.5,
                    "Z": -815.5085
                }
            },
            {
                "AethernetID": 1966106,
                "Front": {
                    "X": -560.6276,
                    "Y": 34.687927,
                    "Z": -799.14294
                }
            },
            {
                "AethernetID": 1966106,
                "Front": {
                    "X": -576.41656,
                    "Y": 53.876858,
                    "Z": -754.6159
                }
            }
        ],
        "341": [
            {
                "AethernetID": 1966113,
                "Front": {
                    "X": -45.72089,
                    "Y": -3.9999964,
                    "Z": -121.69882
                }
            },
            {
                "AethernetID": 1966115,
                "Front": {
                    "X": -53.027378,
                    "Y": 3.9999936,
                    "Z": -89.42796
                }
            },
            {
                "AethernetID": 1966115,
                "Front": {
                    "X": -72.79982,
                    "Y": 5.999999,
                    "Z": -74.79445
                }
            },
            {
                "AethernetID": 1966113,
                "Front": {
                    "X": -88.54482,
                    "Y": -4.0,
                    "Z": -137.96979
                }
            },
            {
                "AethernetID": 1966115,
                "Front": {
                    "X": -105.580894,
                    "Y": 12.0,
                    "Z": -73.76144
                }
            },
            {
                "AethernetID": 1966115,
                "Front": {
                    "X": -48.892113,
                    "Y": 0.0,
                    "Z": -49.64173
                }
            },
            {
                "AethernetID": 1966115,
                "Front": {
                    "X": -85.96264,
                    "Y": 8.0,
                    "Z": -43.009315
                }
            },
            {
                "AethernetID": 1966115,
                "Front": {
                    "X": -100.78543,
                    "Y": 10.001934,
                    "Z": -19.401289
                }
            },
            {
                "AethernetID": 1966115,
                "Front": {
                    "X": -153.92961,
                    "Y": 11.999999,
                    "Z": -53.079384
                }
            },
            {
                "AethernetID": 1966115,
                "Front": {
                    "X": -146.17952,
                    "Y": 15.000004,
                    "Z": -11.056322
                }
            },
            {
                "AethernetID": 1966120,
                "Front": {
                    "X": -143.23729,
                    "Y": 15.0,
                    "Z": 10.667403
                }
            },
            {
                "AethernetID": 1966120,
                "Front": {
                    "X": -131.66849,
                    "Y": 15.000006,
                    "Z": 32.267426
                }
            },
            {
                "AethernetID": 1966120,
                "Front": {
                    "X": -88.769646,
                    "Y": 11.61776,
                    "Z": 32.59629
                }
            },
            {
                "AethernetID": 1966116,
                "Front": {
                    "X": -27.964365,
                    "Y": -20.000248,
                    "Z": 4.702005
                }
            },
            {
                "AethernetID": 1966116,
                "Front": {
                    "X": -1.960088,
                    "Y": -16.018627,
                    "Z": -29.701143
                }
            },
            {
                "AethernetID": 1966116,
                "Front": {
                    "X": 78.34598,
                    "Y": -16.0,
                    "Z": -30.05917
                }
            },
            {
                "AethernetID": 1966116,
                "Front": {
                    "X": 62.992016,
                    "Y": -20.000002,
                    "Z": -13.29576
                }
            },
            {
                "AethernetID": 1966116,
                "Front": {
                    "X": 59.20195,
                    "Y": -24.000004,
                    "Z": 25.527723
                }
            },
            {
                "AethernetID": 1966116,
                "Front": {
                    "X": 26.715912,
                    "Y": -24.0,
                    "Z": 48.375904
                }
            },
            {
                "AethernetID": 1966116,
                "Front": {
                    "X": -3.951771,
                    "Y": -23.999998,
                    "Z": 66.504814
                }
            },
            {
                "AethernetID": 1966114,
                "Front": {
                    "X": 82.0066,
                    "Y": -26.0,
                    "Z": -76.23862
                }
            },
            {
                "AethernetID": 1966119,
                "Front": {
                    "X": 106.721466,
                    "Y": -14.000001,
                    "Z": -22.213255
                }
            },
            {
                "AethernetID": 1966114,
                "Front": {
                    "X": 119.4489,
                    "Y": -17.999998,
                    "Z": -48.307503
                }
            },
            {
                "AethernetID": 1966119,
                "Front": {
                    "X": 148.60245,
                    "Y": -25.999994,
                    "Z": -18.728407
                }
            },
            {
                "AethernetID": 1966119,
                "Front": {
                    "X": 141.22984,
                    "Y": -28.000097,
                    "Z": -0.071287796
                }
            },
            {
                "AethernetID": 1966117,
                "Front": {
                    "X": 133.16745,
                    "Y": -27.99999,
                    "Z": 35.972137
                }
            },
            {
                "AethernetID": 1966117,
                "Front": {
                    "X": 125.99521,
                    "Y": -35.999996,
                    "Z": 58.866375
                }
            },
            {
                "AethernetID": 1966117,
                "Front": {
                    "X": 90.441154,
                    "Y": -36.0,
                    "Z": 75.935646
                }
            },
            {
                "AethernetID": 1966117,
                "Front": {
                    "X": 170.75664,
                    "Y": -44.0,
                    "Z": 27.564026
                }
            },
            {
                "AethernetID": 1966117,
                "Front": {
                    "X": 166.77017,
                    "Y": -40.0,
                    "Z": 48.083
                }
            },
            {
                "AethernetID": 1966121,
                "Front": {
                    "X": -582.76556,
                    "Y": -3.9999962,
                    "Z": -749.29156
                }
            },
            {
                "AethernetID": 1966123,
                "Front": {
                    "X": -614.60297,
                    "Y": 3.999994,
                    "Z": -757.0983
                }
            },
            {
                "AethernetID": 1966123,
                "Front": {
                    "X": -629.26874,
                    "Y": 6.0,
                    "Z": -776.8678
                }
            },
            {
                "AethernetID": 1966121,
                "Front": {
                    "X": -566.1323,
                    "Y": -4.0,
                    "Z": -792.6474
                }
            },
            {
                "AethernetID": 1966123,
                "Front": {
                    "X": -630.126,
                    "Y": 12.0,
                    "Z": -809.72217
                }
            },
            {
                "AethernetID": 1966123,
                "Front": {
                    "X": -654.2725,
                    "Y": 0.0,
                    "Z": -752.8586
                }
            },
            {
                "AethernetID": 1966123,
                "Front": {
                    "X": -661.1394,
                    "Y": 7.999999,
                    "Z": -789.8914
                }
            },
            {
                "AethernetID": 1966123,
                "Front": {
                    "X": -684.38824,
                    "Y": 10.002092,
                    "Z": -804.8892
                }
            },
            {
                "AethernetID": 1966123,
                "Front": {
                    "X": -650.9201,
                    "Y": 11.999999,
                    "Z": -858.3043
                }
            },
            {
                "AethernetID": 1966123,
                "Front": {
                    "X": -692.9052,
                    "Y": 15.000004,
                    "Z": -850.25183
                }
            },
            {
                "AethernetID": 1966128,
                "Front": {
                    "X": -714.5668,
                    "Y": 15.0,
                    "Z": -847.0321
                }
            },
            {
                "AethernetID": 1966128,
                "Front": {
                    "X": -736.53687,
                    "Y": 15.000008,
                    "Z": -835.6975
                }
            },
            {
                "AethernetID": 1966123,
                "Front": {
                    "X": -736.5618,
                    "Y": 11.617771,
                    "Z": -792.7226
                }
            },
            {
                "AethernetID": 1966124,
                "Front": {
                    "X": -708.79926,
                    "Y": -20.000256,
                    "Z": -731.9743
                }
            },
            {
                "AethernetID": 1966124,
                "Front": {
                    "X": -674.4938,
                    "Y": -16.018553,
                    "Z": -705.7746
                }
            },
            {
                "AethernetID": 1966122,
                "Front": {
                    "X": -673.74866,
                    "Y": -16.0,
                    "Z": -625.70325
                }
            },
            {
                "AethernetID": 1966124,
                "Front": {
                    "X": -690.72656,
                    "Y": -20.0,
                    "Z": -641.02014
                }
            },
            {
                "AethernetID": 1966124,
                "Front": {
                    "X": -729.7135,
                    "Y": -24.000004,
                    "Z": -644.294
                }
            },
            {
                "AethernetID": 1966124,
                "Front": {
                    "X": -752.42377,
                    "Y": -23.999998,
                    "Z": -677.0106
                }
            },
            {
                "AethernetID": 1966124,
                "Front": {
                    "X": -770.6601,
                    "Y": -24.0,
                    "Z": -708.25226
                }
            },
            {
                "AethernetID": 1966122,
                "Front": {
                    "X": -627.62726,
                    "Y": -26.0,
                    "Z": -621.9724
                }
            },
            {
                "AethernetID": 1966127,
                "Front": {
                    "X": -681.8768,
                    "Y": -14.000002,
                    "Z": -597.285
                }
            },
            {
                "AethernetID": 1966127,
                "Front": {
                    "X": -655.6477,
                    "Y": -17.999998,
                    "Z": -584.5558
                }
            },
            {
                "AethernetID": 1966127,
                "Front": {
                    "X": -685.3091,
                    "Y": -25.999996,
                    "Z": -555.371
                }
            },
            {
                "AethernetID": 1966127,
                "Front": {
                    "X": -703.9204,
                    "Y": -28.000095,
                    "Z": -562.6698
                }
            },
            {
                "AethernetID": 1966125,
                "Front": {
                    "X": -740.05994,
                    "Y": -27.999992,
                    "Z": -570.8085
                }
            },
            {
                "AethernetID": 1966125,
                "Front": {
                    "X": -762.73755,
                    "Y": -35.999996,
                    "Z": -578.1572
                }
            },
            {
                "AethernetID": 1966125,
                "Front": {
                    "X": -779.98126,
                    "Y": -36.0,
                    "Z": -613.4386
                }
            },
            {
                "AethernetID": 1966125,
                "Front": {
                    "X": -731.4997,
                    "Y": -44.0,
                    "Z": -533.3251
                }
            },
            {
                "AethernetID": 1966125,
                "Front": {
                    "X": -751.97205,
                    "Y": -40.0,
                    "Z": -537.26117
                }
            }
        ],
        "339": [
            {
                "AethernetID": 1966081,
                "Front": {
                    "X": -54.87967,
                    "Y": 39.998055,
                    "Z": -108.19207
                }
            },
            {
                "AethernetID": 1966082,
                "Front": {
                    "X": -123.99958,
                    "Y": 33.9071,
                    "Z": -80.03813
                }
            },
            {
                "AethernetID": 1966082,
                "Front": {
                    "X": -96.00657,
                    "Y": 30.579378,
                    "Z": -75.27464
                }
            },
            {
                "AethernetID": 1966086,
                "Front": {
                    "X": -74.80576,
                    "Y": 18.000732,
                    "Z": -16.012432
                }
            },
            {
                "AethernetID": 1966088,
                "Front": {
                    "X": -123.68238,
                    "Y": 18.110334,
                    "Z": 13.825798
                }
            },
            {
                "AethernetID": 1966086,
                "Front": {
                    "X": -49.03028,
                    "Y": 13.119313,
                    "Z": 9.003218
                }
            },
            {
                "AethernetID": 1966086,
                "Front": {
                    "X": -39.95934,
                    "Y": 23.991621,
                    "Z": -39.01766
                }
            },
            {
                "AethernetID": 1966082,
                "Front": {
                    "X": -25.11606,
                    "Y": 35.99858,
                    "Z": -88.064865
                }
            },
            {
                "AethernetID": 1966083,
                "Front": {
                    "X": 52.883713,
                    "Y": 37.998264,
                    "Z": -96.04967
                }
            },
            {
                "AethernetID": 1966083,
                "Front": {
                    "X": 68.20711,
                    "Y": 39.996716,
                    "Z": -107.80365
                }
            },
            {
                "AethernetID": 1966084,
                "Front": {
                    "X": 16.876608,
                    "Y": 24.999863,
                    "Z": -52.053047
                }
            },
            {
                "AethernetID": 1966087,
                "Front": {
                    "X": 48.215233,
                    "Y": 25.09768,
                    "Z": -45.43909
                }
            },
            {
                "AethernetID": 1966087,
                "Front": {
                    "X": 68.00643,
                    "Y": 17.999966,
                    "Z": -19.055256
                }
            },
            {
                "AethernetID": 1966087,
                "Front": {
                    "X": 101.68895,
                    "Y": 28.795921,
                    "Z": -56.33135
                }
            },
            {
                "AethernetID": 1966083,
                "Front": {
                    "X": 128.2609,
                    "Y": 43.997574,
                    "Z": -84.04163
                }
            },
            {
                "AethernetID": 1966087,
                "Front": {
                    "X": 122.88412,
                    "Y": 27.999958,
                    "Z": -37.890335
                }
            },
            {
                "AethernetID": 1966087,
                "Front": {
                    "X": 98.91951,
                    "Y": 21.992542,
                    "Z": -23.836407
                }
            },
            {
                "AethernetID": 1966087,
                "Front": {
                    "X": 86.34286,
                    "Y": 16.077564,
                    "Z": 3.8021712
                }
            },
            {
                "AethernetID": 1966084,
                "Front": {
                    "X": 36.31606,
                    "Y": 6.002165,
                    "Z": 39.107254
                }
            },
            {
                "AethernetID": 1966084,
                "Front": {
                    "X": 57.9756,
                    "Y": 4.0672703,
                    "Z": 49.94343
                }
            },
            {
                "AethernetID": 1966084,
                "Front": {
                    "X": 77.6992,
                    "Y": 3.0382283,
                    "Z": 64.305984
                }
            },
            {
                "AethernetID": 1966085,
                "Front": {
                    "X": 133.1901,
                    "Y": 18.000622,
                    "Z": 59.959072
                }
            },
            {
                "AethernetID": 1966085,
                "Front": {
                    "X": 125.55448,
                    "Y": 17.785854,
                    "Z": 31.97164
                }
            },
            {
                "AethernetID": 1966085,
                "Front": {
                    "X": 150.0264,
                    "Y": 22.000235,
                    "Z": 7.0527167
                }
            },
            {
                "AethernetID": 1966085,
                "Front": {
                    "X": 175.0041,
                    "Y": 31.999025,
                    "Z": 28.253172
                }
            },
            {
                "AethernetID": 1966085,
                "Front": {
                    "X": 154.83301,
                    "Y": 27.99951,
                    "Z": 56.099983
                }
            },
            {
                "AethernetID": 1966085,
                "Front": {
                    "X": 186.18686,
                    "Y": 35.99852,
                    "Z": 7.2202373
                }
            },
            {
                "AethernetID": 1966085,
                "Front": {
                    "X": 199.91063,
                    "Y": 39.99808,
                    "Z": 36.93202
                }
            },
            {
                "AethernetID": 1966085,
                "Front": {
                    "X": 178.82649,
                    "Y": 37.99826,
                    "Z": 71.95123
                }
            },
            {
                "AethernetID": 1966085,
                "Front": {
                    "X": 129.63866,
                    "Y": 18.000723,
                    "Z": 82.36208
                }
            },
            {
                "AethernetID": 1966089,
                "Front": {
                    "X": -595.9776,
                    "Y": 39.998055,
                    "Z": -758.9319
                }
            },
            {
                "AethernetID": 1966090,
                "Front": {
                    "X": -623.9302,
                    "Y": 33.90823,
                    "Z": -827.9792
                }
            },
            {
                "AethernetID": 1966090,
                "Front": {
                    "X": -628.3676,
                    "Y": 30.589533,
                    "Z": -800.15216
                }
            },
            {
                "AethernetID": 1966094,
                "Front": {
                    "X": -687.9236,
                    "Y": 18.000734,
                    "Z": -778.90265
                }
            },
            {
                "AethernetID": 1966096,
                "Front": {
                    "X": -717.8128,
                    "Y": 18.096336,
                    "Z": -827.4982
                }
            },
            {
                "AethernetID": 1966094,
                "Front": {
                    "X": -712.936,
                    "Y": 13.162883,
                    "Z": -752.90314
                }
            },
            {
                "AethernetID": 1966094,
                "Front": {
                    "X": -664.92035,
                    "Y": 23.991623,
                    "Z": -743.93695
                }
            },
            {
                "AethernetID": 1966090,
                "Front": {
                    "X": -616.0959,
                    "Y": 35.99858,
                    "Z": -729.04755
                }
            },
            {
                "AethernetID": 1966091,
                "Front": {
                    "X": -608.19763,
                    "Y": 37.998188,
                    "Z": -650.9514
                }
            },
            {
                "AethernetID": 1966091,
                "Front": {
                    "X": -596.23267,
                    "Y": 39.998234,
                    "Z": -636.1092
                }
            },
            {
                "AethernetID": 1966092,
                "Front": {
                    "X": -652.0157,
                    "Y": 24.99986,
                    "Z": -686.9312
                }
            },
            {
                "AethernetID": 1966095,
                "Front": {
                    "X": -658.3998,
                    "Y": 25.169823,
                    "Z": -655.8979
                }
            },
            {
                "AethernetID": 1966095,
                "Front": {
                    "X": -685.18915,
                    "Y": 17.999966,
                    "Z": -636.04254
                }
            },
            {
                "AethernetID": 1966095,
                "Front": {
                    "X": -647.6171,
                    "Y": 28.82019,
                    "Z": -602.55115
                }
            },
            {
                "AethernetID": 1966091,
                "Front": {
                    "X": -620.0214,
                    "Y": 43.997574,
                    "Z": -575.8648
                }
            },
            {
                "AethernetID": 1966095,
                "Front": {
                    "X": -666.0302,
                    "Y": 27.999958,
                    "Z": -581.2175
                }
            },
            {
                "AethernetID": 1966095,
                "Front": {
                    "X": -680.0979,
                    "Y": 21.992542,
                    "Z": -604.96216
                }
            },
            {
                "AethernetID": 1966095,
                "Front": {
                    "X": -707.86194,
                    "Y": 16.125505,
                    "Z": -617.75653
                }
            },
            {
                "AethernetID": 1966092,
                "Front": {
                    "X": -743.16235,
                    "Y": 6.002165,
                    "Z": -667.6114
                }
            },
            {
                "AethernetID": 1966092,
                "Front": {
                    "X": -754.0562,
                    "Y": 4.0676804,
                    "Z": -645.982
                }
            },
            {
                "AethernetID": 1966092,
                "Front": {
                    "X": -768.40173,
                    "Y": 3.0405076,
                    "Z": -626.4234
                }
            },
            {
                "AethernetID": 1966093,
                "Front": {
                    "X": -764.0846,
                    "Y": 18.000694,
                    "Z": -570.7609
                }
            },
            {
                "AethernetID": 1966093,
                "Front": {
                    "X": -735.9244,
                    "Y": 17.822828,
                    "Z": -578.72076
                }
            },
            {
                "AethernetID": 1966093,
                "Front": {
                    "X": -711.0343,
                    "Y": 22.000235,
                    "Z": -553.98737
                }
            },
            {
                "AethernetID": 1966093,
                "Front": {
                    "X": -731.90314,
                    "Y": 31.999025,
                    "Z": -528.95776
                }
            },
            {
                "AethernetID": 1966093,
                "Front": {
                    "X": -760.10504,
                    "Y": 27.99951,
                    "Z": -549.145
                }
            },
            {
                "AethernetID": 1966093,
                "Front": {
                    "X": -710.99255,
                    "Y": 35.998528,
                    "Z": -517.9467
                }
            },
            {
                "AethernetID": 1966093,
                "Front": {
                    "X": -741.1705,
                    "Y": 39.998043,
                    "Z": -503.94635
                }
            },
            {
                "AethernetID": 1966093,
                "Front": {
                    "X": -776.02496,
                    "Y": 37.99826,
                    "Z": -525.1236
                }
            },
            {
                "AethernetID": 1966093,
                "Front": {
                    "X": -786.4939,
                    "Y": 18.000721,
                    "Z": -574.26276
                }
            }
        ],
        "979": [
            {
                "AethernetID": 1966145,
                "Front": {
                    "X": 90.03777,
                    "Y": -19.83884,
                    "Z": 160.69789
                }
            },
            {
                "AethernetID": 1966146,
                "Front": {
                    "X": 144.01161,
                    "Y": -39.82345,
                    "Z": 149.2722
                }
            },
            {
                "AethernetID": 1966145,
                "Front": {
                    "X": 78.83922,
                    "Y": -29.839083,
                    "Z": 125.30259
                }
            },
            {
                "AethernetID": 1966146,
                "Front": {
                    "X": 117.3159,
                    "Y": -29.84593,
                    "Z": 78.065575
                }
            },
            {
                "AethernetID": 1966146,
                "Front": {
                    "X": 178.8777,
                    "Y": -49.929287,
                    "Z": 68.420265
                }
            },
            {
                "AethernetID": 1966146,
                "Front": {
                    "X": 184.08772,
                    "Y": -49.951862,
                    "Z": 60.657967
                }
            },
            {
                "AethernetID": 1966151,
                "Front": {
                    "X": 137.3288,
                    "Y": -29.852533,
                    "Z": 41.912376
                }
            },
            {
                "AethernetID": 1966148,
                "Front": {
                    "X": -19.434114,
                    "Y": -19.794035,
                    "Z": 97.58507
                }
            },
            {
                "AethernetID": 1966161,
                "Front": {
                    "X": -5.355879,
                    "Y": -19.875317,
                    "Z": 72.43681
                }
            },
            {
                "AethernetID": 1966161,
                "Front": {
                    "X": -23.055603,
                    "Y": -19.784945,
                    "Z": 19.802744
                }
            },
            {
                "AethernetID": 1966148,
                "Front": {
                    "X": -70.9558,
                    "Y": -9.856712,
                    "Z": 151.33687
                }
            },
            {
                "AethernetID": 1966148,
                "Front": {
                    "X": -90.69172,
                    "Y": 0.14093816,
                    "Z": 94.12374
                }
            },
            {
                "AethernetID": 1966148,
                "Front": {
                    "X": -81.01606,
                    "Y": 0.20341384,
                    "Z": 58.219906
                }
            },
            {
                "AethernetID": 1966161,
                "Front": {
                    "X": -22.936668,
                    "Y": -19.9,
                    "Z": -19.569387
                }
            },
            {
                "AethernetID": 1966161,
                "Front": {
                    "X": 0.29877645,
                    "Y": -19.750906,
                    "Z": -66.81872
                }
            },
            {
                "AethernetID": 1966150,
                "Front": {
                    "X": -27.417807,
                    "Y": -9.9293585,
                    "Z": -103.33152
                }
            },
            {
                "AethernetID": 1966150,
                "Front": {
                    "X": -65.7283,
                    "Y": 0.17681336,
                    "Z": -43.143726
                }
            },
            {
                "AethernetID": 1966150,
                "Front": {
                    "X": -99.43927,
                    "Y": 10.17468,
                    "Z": -96.698685
                }
            },
            {
                "AethernetID": 1966150,
                "Front": {
                    "X": -29.842735,
                    "Y": 0.2356093,
                    "Z": -146.11061
                }
            },
            {
                "AethernetID": 1966150,
                "Front": {
                    "X": -76.805885,
                    "Y": 0.11035955,
                    "Z": -130.59906
                }
            },
            {
                "AethernetID": 1966150,
                "Front": {
                    "X": -71.92132,
                    "Y": 10.168006,
                    "Z": -169.71117
                }
            },
            {
                "AethernetID": 1966150,
                "Front": {
                    "X": -111.50823,
                    "Y": 20.06369,
                    "Z": -136.05547
                }
            },
            {
                "AethernetID": 1966147,
                "Front": {
                    "X": 100.62527,
                    "Y": -19.842741,
                    "Z": -27.665998
                }
            },
            {
                "AethernetID": 1966152,
                "Front": {
                    "X": 121.47655,
                    "Y": -19.9,
                    "Z": -74.47288
                }
            },
            {
                "AethernetID": 1966152,
                "Front": {
                    "X": 88.03083,
                    "Y": -19.885105,
                    "Z": -71.60787
                }
            },
            {
                "AethernetID": 1966151,
                "Front": {
                    "X": 184.9472,
                    "Y": -39.86624,
                    "Z": -33.644535
                }
            },
            {
                "AethernetID": 1966152,
                "Front": {
                    "X": 137.73859,
                    "Y": -29.766802,
                    "Z": -90.76175
                }
            },
            {
                "AethernetID": 1966152,
                "Front": {
                    "X": 60.2827,
                    "Y": 0.17113817,
                    "Z": -135.17671
                }
            },
            {
                "AethernetID": 1966152,
                "Front": {
                    "X": 52.033028,
                    "Y": 0.26187623,
                    "Z": -159.89384
                }
            },
            {
                "AethernetID": 1966152,
                "Front": {
                    "X": 93.10805,
                    "Y": 0.20020962,
                    "Z": -149.77385
                }
            },
            {
                "AethernetID": 1966153,
                "Front": {
                    "X": -864.6775,
                    "Y": -19.849327,
                    "Z": -613.9179
                }
            },
            {
                "AethernetID": 1966154,
                "Front": {
                    "X": -853.22955,
                    "Y": -39.801514,
                    "Z": -559.74896
                }
            },
            {
                "AethernetID": 1966153,
                "Front": {
                    "X": -829.24225,
                    "Y": -29.808073,
                    "Z": -624.89264
                }
            },
            {
                "AethernetID": 1966154,
                "Front": {
                    "X": -782.0807,
                    "Y": -29.84541,
                    "Z": -586.6851
                }
            },
            {
                "AethernetID": 1966154,
                "Front": {
                    "X": -772.7689,
                    "Y": -49.802345,
                    "Z": -525.24225
                }
            },
            {
                "AethernetID": 1966154,
                "Front": {
                    "X": -764.7319,
                    "Y": -49.914925,
                    "Z": -519.86707
                }
            },
            {
                "AethernetID": 1966159,
                "Front": {
                    "X": -745.7866,
                    "Y": -29.87207,
                    "Z": -566.6332
                }
            },
            {
                "AethernetID": 1966156,
                "Front": {
                    "X": -801.52466,
                    "Y": -19.756783,
                    "Z": -723.48016
                }
            },
            {
                "AethernetID": 1966162,
                "Front": {
                    "X": -776.3084,
                    "Y": -19.804707,
                    "Z": -709.2997
                }
            },
            {
                "AethernetID": 1966162,
                "Front": {
                    "X": -723.7172,
                    "Y": -19.828905,
                    "Z": -727.1799
                }
            },
            {
                "AethernetID": 1966156,
                "Front": {
                    "X": -855.27783,
                    "Y": -9.826358,
                    "Z": -775.1722
                }
            },
            {
                "AethernetID": 1966156,
                "Front": {
                    "X": -798.01056,
                    "Y": 0.29518783,
                    "Z": -794.97864
                }
            },
            {
                "AethernetID": 1966156,
                "Front": {
                    "X": -762.17346,
                    "Y": 0.22728074,
                    "Z": -784.9486
                }
            },
            {
                "AethernetID": 1966162,
                "Front": {
                    "X": -684.375,
                    "Y": -19.876305,
                    "Z": -726.72754
                }
            },
            {
                "AethernetID": 1966162,
                "Front": {
                    "X": -637.2652,
                    "Y": -19.836123,
                    "Z": -703.53204
                }
            },
            {
                "AethernetID": 1966158,
                "Front": {
                    "X": -600.58856,
                    "Y": -9.883326,
                    "Z": -731.5831
                }
            },
            {
                "AethernetID": 1966158,
                "Front": {
                    "X": -660.8085,
                    "Y": 0.20525658,
                    "Z": -769.7836
                }
            },
            {
                "AethernetID": 1966158,
                "Front": {
                    "X": -607.2865,
                    "Y": 10.165059,
                    "Z": -803.42676
                }
            },
            {
                "AethernetID": 1966158,
                "Front": {
                    "X": -557.92535,
                    "Y": 0.19412172,
                    "Z": -733.762
                }
            },
            {
                "AethernetID": 1966158,
                "Front": {
                    "X": -573.24066,
                    "Y": 0.19274151,
                    "Z": -780.8265
                }
            },
            {
                "AethernetID": 1966158,
                "Front": {
                    "X": -534.246,
                    "Y": 10.190043,
                    "Z": -776.0322
                }
            },
            {
                "AethernetID": 1966158,
                "Front": {
                    "X": -567.8494,
                    "Y": 20.217623,
                    "Z": -815.80774
                }
            },
            {
                "AethernetID": 1966155,
                "Front": {
                    "X": -676.2198,
                    "Y": -19.740396,
                    "Z": -603.2116
                }
            },
            {
                "AethernetID": 1966160,
                "Front": {
                    "X": -629.7647,
                    "Y": -19.865837,
                    "Z": -582.61145
                }
            },
            {
                "AethernetID": 1966160,
                "Front": {
                    "X": -632.21234,
                    "Y": -19.792702,
                    "Z": -615.8561
                }
            },
            {
                "AethernetID": 1966159,
                "Front": {
                    "X": -670.2912,
                    "Y": -39.833202,
                    "Z": -518.8697
                }
            },
            {
                "AethernetID": 1966160,
                "Front": {
                    "X": -613.2919,
                    "Y": -29.828962,
                    "Z": -566.3715
                }
            },
            {
                "AethernetID": 1966160,
                "Front": {
                    "X": -568.9539,
                    "Y": 0.20202708,
                    "Z": -643.7774
                }
            },
            {
                "AethernetID": 1966160,
                "Front": {
                    "X": -544.2598,
                    "Y": 0.18289113,
                    "Z": -651.87744
                }
            },
            {
                "AethernetID": 1966160,
                "Front": {
                    "X": -554.2744,
                    "Y": 0.17539501,
                    "Z": -610.92413
                }
            }
        ],
        "641": [
            {
                "AethernetID": 1966135,
                "Front": {
                    "X": -17.639841,
                    "Y": 2.001914,
                    "Z": 120.453705
                }
            },
            {
                "AethernetID": 1966135,
                "Front": {
                    "X": -13.357594,
                    "Y": 14.072637,
                    "Z": 78.579735
                }
            },
            {
                "AethernetID": 1966135,
                "Front": {
                    "X": 16.72184,
                    "Y": 5.999982,
                    "Z": 130.41754
                }
            },
            {
                "AethernetID": 1966135,
                "Front": {
                    "X": 13.370714,
                    "Y": 20.0,
                    "Z": 67.7013
                }
            },
            {
                "AethernetID": 1966135,
                "Front": {
                    "X": 33.680065,
                    "Y": 19.999985,
                    "Z": 74.293015
                }
            },
            {
                "AethernetID": 1966136,
                "Front": {
                    "X": 45.09415,
                    "Y": 9.999998,
                    "Z": 111.75111
                }
            },
            {
                "AethernetID": 1966136,
                "Front": {
                    "X": 50.10161,
                    "Y": 9.999995,
                    "Z": 119.148224
                }
            },
            {
                "AethernetID": 1966133,
                "Front": {
                    "X": 101.1746,
                    "Y": 10.120041,
                    "Z": 116.17626
                }
            },
            {
                "AethernetID": 1966133,
                "Front": {
                    "X": 100.6273,
                    "Y": 15.99987,
                    "Z": 85.580505
                }
            },
            {
                "AethernetID": 1966133,
                "Front": {
                    "X": 108.89991,
                    "Y": 22.0,
                    "Z": 61.019768
                }
            },
            {
                "AethernetID": 1966133,
                "Front": {
                    "X": 77.80867,
                    "Y": 22.0,
                    "Z": 53.54726
                }
            },
            {
                "AethernetID": 1966133,
                "Front": {
                    "X": 52.633656,
                    "Y": 25.999994,
                    "Z": 33.77999
                }
            },
            {
                "AethernetID": 1966133,
                "Front": {
                    "X": 58.91301,
                    "Y": 30.096643,
                    "Z": -0.6818796
                }
            },
            {
                "AethernetID": 1966133,
                "Front": {
                    "X": 95.903305,
                    "Y": 30.0,
                    "Z": 15.075542
                }
            },
            {
                "AethernetID": 1966133,
                "Front": {
                    "X": 119.24451,
                    "Y": 33.999996,
                    "Z": 20.062805
                }
            },
            {
                "AethernetID": 1966133,
                "Front": {
                    "X": 118.319954,
                    "Y": 40.0,
                    "Z": -12.354942
                }
            },
            {
                "AethernetID": 1966129,
                "Front": {
                    "X": -116.22784,
                    "Y": 2.0,
                    "Z": 67.551765
                }
            },
            {
                "AethernetID": 1966134,
                "Front": {
                    "X": -98.037025,
                    "Y": 14.106043,
                    "Z": 29.137518
                }
            },
            {
                "AethernetID": 1966129,
                "Front": {
                    "X": -123.11596,
                    "Y": 1.9999897,
                    "Z": 61.97561
                }
            },
            {
                "AethernetID": 1966134,
                "Front": {
                    "X": -117.51733,
                    "Y": 10.0,
                    "Z": 19.40547
                }
            },
            {
                "AethernetID": 1966134,
                "Front": {
                    "X": -167.25577,
                    "Y": 6.0,
                    "Z": 9.572615
                }
            },
            {
                "AethernetID": 1966134,
                "Front": {
                    "X": -167.13431,
                    "Y": 6.0,
                    "Z": 1.824494
                }
            },
            {
                "AethernetID": 1966131,
                "Front": {
                    "X": -141.84755,
                    "Y": 15.999994,
                    "Z": -58.931656
                }
            },
            {
                "AethernetID": 1966131,
                "Front": {
                    "X": -109.20625,
                    "Y": 15.999998,
                    "Z": -39.98344
                }
            },
            {
                "AethernetID": 1966131,
                "Front": {
                    "X": -91.197685,
                    "Y": 14.0,
                    "Z": -20.45372
                }
            },
            {
                "AethernetID": 1966131,
                "Front": {
                    "X": -105.93694,
                    "Y": 15.999996,
                    "Z": -46.914864
                }
            },
            {
                "AethernetID": 1966131,
                "Front": {
                    "X": -59.110336,
                    "Y": 19.99999,
                    "Z": -42.130737
                }
            },
            {
                "AethernetID": 1966130,
                "Front": {
                    "X": -74.9458,
                    "Y": 25.0,
                    "Z": -100.04642
                }
            },
            {
                "AethernetID": 1966130,
                "Front": {
                    "X": -130.0184,
                    "Y": 25.160213,
                    "Z": -86.43976
                }
            },
            {
                "AethernetID": 1966130,
                "Front": {
                    "X": -141.46347,
                    "Y": 29.999998,
                    "Z": -104.35433
                }
            },
            {
                "AethernetID": 1966141,
                "Front": {
                    "X": -824.28656,
                    "Y": 2.002423,
                    "Z": -721.6977
                }
            },
            {
                "AethernetID": 1966141,
                "Front": {
                    "X": -782.5326,
                    "Y": 14.050001,
                    "Z": -717.29645
                }
            },
            {
                "AethernetID": 1966141,
                "Front": {
                    "X": -834.35126,
                    "Y": 5.999981,
                    "Z": -687.3446
                }
            },
            {
                "AethernetID": 1966141,
                "Front": {
                    "X": -771.4175,
                    "Y": 20.05,
                    "Z": -690.5895
                }
            },
            {
                "AethernetID": 1966141,
                "Front": {
                    "X": -778.1652,
                    "Y": 19.999979,
                    "Z": -670.4081
                }
            },
            {
                "AethernetID": 1966143,
                "Front": {
                    "X": -816.44464,
                    "Y": 10.07,
                    "Z": -658.912
                }
            },
            {
                "AethernetID": 1966143,
                "Front": {
                    "X": -823.0448,
                    "Y": 9.999995,
                    "Z": -654.08093
                }
            },
            {
                "AethernetID": 1966143,
                "Front": {
                    "X": -820.17035,
                    "Y": 10.107784,
                    "Z": -602.8512
                }
            },
            {
                "AethernetID": 1966143,
                "Front": {
                    "X": -789.56976,
                    "Y": 15.99987,
                    "Z": -603.4801
                }
            },
            {
                "AethernetID": 1966144,
                "Front": {
                    "X": -764.80225,
                    "Y": 22.0,
                    "Z": -595.09283
                }
            },
            {
                "AethernetID": 1966144,
                "Front": {
                    "X": -757.81226,
                    "Y": 22.05,
                    "Z": -626.5431
                }
            },
            {
                "AethernetID": 1966144,
                "Front": {
                    "X": -737.7357,
                    "Y": 25.999998,
                    "Z": -651.47974
                }
            },
            {
                "AethernetID": 1966144,
                "Front": {
                    "X": -703.17865,
                    "Y": 30.156832,
                    "Z": -645.115
                }
            },
            {
                "AethernetID": 1966144,
                "Front": {
                    "X": -719.0055,
                    "Y": 30.0,
                    "Z": -608.1642
                }
            },
            {
                "AethernetID": 1966144,
                "Front": {
                    "X": -723.9821,
                    "Y": 34.0,
                    "Z": -584.8257
                }
            },
            {
                "AethernetID": 1966144,
                "Front": {
                    "X": -691.5069,
                    "Y": 40.0,
                    "Z": -585.5689
                }
            },
            {
                "AethernetID": 1966139,
                "Front": {
                    "X": -771.64716,
                    "Y": 1.9999995,
                    "Z": -820.02435
                }
            },
            {
                "AethernetID": 1966137,
                "Front": {
                    "X": -732.99585,
                    "Y": 14.088533,
                    "Z": -801.9289
                }
            },
            {
                "AethernetID": 1966139,
                "Front": {
                    "X": -765.823,
                    "Y": 1.9999886,
                    "Z": -827.0197
                }
            },
            {
                "AethernetID": 1966137,
                "Front": {
                    "X": -723.4309,
                    "Y": 10.0,
                    "Z": -821.57025
                }
            },
            {
                "AethernetID": 1966137,
                "Front": {
                    "X": -713.5237,
                    "Y": 6.0,
                    "Z": -871.27814
                }
            },
            {
                "AethernetID": 1966137,
                "Front": {
                    "X": -705.9348,
                    "Y": 6.0,
                    "Z": -870.8666
                }
            },
            {
                "AethernetID": 1966140,
                "Front": {
                    "X": -644.8239,
                    "Y": 15.999996,
                    "Z": -845.9563
                }
            },
            {
                "AethernetID": 1966140,
                "Front": {
                    "X": -664.091,
                    "Y": 16.024416,
                    "Z": -813.2712
                }
            },
            {
                "AethernetID": 1966140,
                "Front": {
                    "X": -683.681,
                    "Y": 13.999999,
                    "Z": -795.26886
                }
            },
            {
                "AethernetID": 1966140,
                "Front": {
                    "X": -657.1277,
                    "Y": 15.999996,
                    "Z": -810.15436
                }
            },
            {
                "AethernetID": 1966140,
                "Front": {
                    "X": -662.2881,
                    "Y": 20.069998,
                    "Z": -762.8696
                }
            },
            {
                "AethernetID": 1966138,
                "Front": {
                    "X": -603.8531,
                    "Y": 25.0,
                    "Z": -778.98315
                }
            },
            {
                "AethernetID": 1966138,
                "Front": {
                    "X": -617.71295,
                    "Y": 25.026217,
                    "Z": -834.21747
                }
            },
            {
                "AethernetID": 1966138,
                "Front": {
                    "X": -599.6957,
                    "Y": 29.999998,
                    "Z": -845.50073
                }
            }
        ]
    }
}